{
  "type": "Feature",
  "properties": {
    "wof:name":"Mapzen",
    "wof:placetype":"venue"
},
  "geometry": {"coordinates":[-73.990323543549,40.74405440413],"type":"Point"}
}